setup.py
bltz_mon.egg-info/PKG-INFO
bltz_mon.egg-info/SOURCES.txt
bltz_mon.egg-info/dependency_links.txt
bltz_mon.egg-info/top_level.txt
mon/__init__.py