Metadata-Version: 2.1
Name: bltz-mon
Version: 1.0
Summary: yjcwefewf
Home-page: 
Author: Blitz
Author-email: 
